twibooru/__init__.py
twibooru/filters.py
twibooru/forums.py
twibooru/galleries.py
twibooru/gallery.py
twibooru/helpers.py
twibooru/image.py
twibooru/post.py
twibooru/post_image.py
twibooru/posts.py
twibooru/profile.py
twibooru/query.py
twibooru/request.py
twibooru/search.py
twibooru/sort.py
twibooru/tag.py
twibooru/tags.py
twibooru/user.py
Twibooru_Py-0.1.0.dist-info/LICENSE.txt
Twibooru_Py-0.1.0.dist-info/METADATA
Twibooru_Py-0.1.0.dist-info/WHEEL
Twibooru_Py-0.1.0.dist-info/top_level.txt
Twibooru_Py-0.1.0.dist-info/RECORD
