Metadata-Version: 2.1
Name: Twibooru-Py
Version: 0.1.0
Summary: Python bindings for Twibooru's API
Home-page: https://github.com/Atronar/Twibooru-Py
Author: ATroN
Author-email: master.atron@gmail.com
License: Simplified BSD License
Platform: any
Classifier: Development Status :: 4 - Beta
Classifier: Intended Audience :: Developers
Classifier: Operating System :: OS Independent
Classifier: License :: OSI Approved :: BSD License
Classifier: Topic :: Software Development :: Libraries :: Python Modules
Classifier: Programming Language :: Python :: 3
Requires-Python: >=3.6
Requires-Dist: requests
